ndscope/__init__.py
ndscope/__main__.py
ndscope/__version__.py
ndscope/_qt.py
ndscope/axisCtrlTemplate.ui
ndscope/cache.py
ndscope/channel_config.ui
ndscope/channel_config_dialog.ui
ndscope/channel_list.ui
ndscope/channel_select.py
ndscope/channel_select_dialog.ui
ndscope/const.py
ndscope/crosshair.py
ndscope/cursors.py
ndscope/data.py
ndscope/dialog.py
ndscope/dialog_nds_auth.ui
ndscope/dialog_nds_ontape.ui
ndscope/exceptions.py
ndscope/export.py
ndscope/kerberos.py
ndscope/legend.py
ndscope/math_config.py
ndscope/math_config.ui
ndscope/nds.py
ndscope/plot.py
ndscope/plotMenu.py
ndscope/primary_view.py
ndscope/result.py
ndscope/ruff.toml
ndscope/scope.py
ndscope/scope.ui
ndscope/template.py
ndscope/trigger.py
ndscope/util.py
ndscope/dtt/__init__.py
ndscope/dtt/channel_trend_id.py
ndscope/dtt/dtt.py
ndscope/test/__init__.py
ndscope/test/test_cache.py
ndscope/test/test_cli.py
ndscope/test/test_data_flow.py
ndscope/test/test_layout.py
ndscope/test/test_plot.py
ndscope/test/test_util.py
ndscope/test/test_window.py
ndscope/test/templates/test.yaml
ndscope/test/templates/test0.yaml
ndscope/test/templates/test1-1.yaml
ndscope/test/templates/test1-2.yaml
ndscope/test/templates/test1-3.yaml
ndscope/test/templates/test1.yaml
ndscope/test/templates/test2.stp
ndscope/test/templates/test2.yaml
ndscope/test/templates/test3.txt
ndscope/test/templates/test3.yaml
ndscope/test/templates/test4.xml
ndscope/test/templates/test4.yaml
ndscope-0.20.6.dist-info/licenses/COPYING
ndscope-0.20.6.dist-info/licenses/COPYING-GPL-3
ndscope-0.20.6.dist-info/METADATA
ndscope-0.20.6.dist-info/WHEEL
ndscope-0.20.6.dist-info/entry_points.txt
ndscope-0.20.6.dist-info/top_level.txt
ndscope-0.20.6.dist-info/RECORD
