Metadata-Version: 2.4
Name: ndscope
Version: 0.20.6
Summary: Next-generation NDS time series plotting
Author-email: Jameson Graef Rollins <jameson.rollins@ligo.org>, Patrick Thomas <patrick.thomas@ligo.org>, Erik von Reis <erik.vonreis@ligo.org>
Maintainer-email: Jameson Graef Rollins <jameson.rollins@ligo.org>, Patrick Thomas <patrick.thomas@ligo.org>, Erik von Reis <erik.vonreis@ligo.org>
License-Expression: GPL-3.0-or-later
Project-URL: Homepage, https://git.ligo.org/cds/software/ndscope
Project-URL: Repository, https://git.ligo.org/cds/software/ndscope.git
Project-URL: Bug Tracker, https://git.ligo.org/cds/software/ndscope/-/issues
Project-URL: Changelog, https://git.ligo.org/cds/software/ndscope/-/blob/master/CHANGELOG.md
Classifier: Development Status :: 5 - Production/Stable
Classifier: Natural Language :: English
Classifier: Operating System :: OS Independent
Classifier: Programming Language :: Python
Requires-Python: >=3.9
License-File: COPYING
License-File: COPYING-GPL-3
Requires-Dist: cairosvg
Requires-Dist: dttlib>=0.10.3
Requires-Dist: gpstime
Requires-Dist: h5py
Requires-Dist: matplotlib
Requires-Dist: numpy
Requires-Dist: pyqt5
Requires-Dist: pyqtgraph
Requires-Dist: python-dateutil
Requires-Dist: pyyaml
Requires-Dist: QtPy
Requires-Dist: rapidfuzz
Requires-Dist: scipy
Requires-Dist: setproctitle
Requires-Dist: setuptools_scm
Dynamic: license-file
